{"stats":{"minecraft:used":{"minecraft:diamond_pickaxe":1,"spartanweaponry:copper_javelin":2,"minecraft:nether_wart_block":1,"minecraft:soul_sand":1,"minecraft:baked_potato":2,"alexsmobs:animal_dictionary":1,"minecraft:cobbled_deepslate":16},"minecraft:custom":{"minecraft:time_since_rest":46497,"minecraft:open_chest":3,"minecraft:crouch_one_cm":1684,"minecraft:play_time":49049,"minecraft:sprint_one_cm":17353,"minecraft:damage_taken":650,"minecraft:deaths":2,"minecraft:walk_one_cm":25397,"minecraft:sneak_time":695,"minecraft:walk_under_water_one_cm":1460,"minecraft:drop":3,"minecraft:jump":85,"minecraft:damage_dealt":26,"minecraft:leave_game":9,"minecraft:time_since_death":45967,"minecraft:walk_on_water_one_cm":3095,"minecraft:climb_one_cm":1674,"minecraft:total_world_time":49049,"minecraft:swim_one_cm":13938,"minecraft:fall_one_cm":1511,"minecraft:fly_one_cm":13232},"minecraft:picked_up":{"minecraft:cobbled_deepslate":1,"minecraft:nether_wart_block":2,"minecraft:soul_sand":3},"minecraft:killed_by":{"minecraft:skeleton":1},"minecraft:dropped":{"gravestone:obituary":1,"minecraft:soul_sand":2,"minecraft:nether_wart_block":1},"minecraft:mined":{"minecraft:weeping_vines":1,"minecraft:soul_sand":3,"minecraft:nether_wart_block":2,"minecraft:cobbled_deepslate":1}},"DataVersion":3465}